
{
  "id": "reading-b1-002",
  "level": "b1",
  "type": "grouped-mcq",
  "title": "Digitalisierung im Alltag",
  "subtitle": "Wie digitale Tools unser Leben und Arbeiten verändern",
  "text": "In den letzten Jahren hat die Digitalisierung unser tägliches Leben stark verändert.\nViele Menschen nutzen heute digitale Geräte wie Smartphones, Tablets oder Laptops nicht nur bei der Arbeit,\nsondern auch in ihrer Freizeit. Nachrichten werden online gelesen, Kleidung wird über das Internet bestellt\nund mit Freunden kommuniziert man über soziale Netzwerke. Auch im Gesundheitsbereich hat sich vieles verändert.\nEs gibt Apps, die an die Einnahme von Medikamenten erinnern oder den Blutdruck messen können.\nÄltere Menschen profitieren besonders von diesen digitalen Hilfen, auch wenn sie sich oft erst an die neuen Technologien gewöhnen müssen.\n\nIm Berufsleben ist Digitalisierung nicht mehr wegzudenken. Viele Unternehmen ermöglichen Homeoffice, und Online-Meetings ersetzen oft persönliche Besprechungen. Dokumente werden in der Cloud gespeichert, was die Zusammenarbeit erleichtert.\nAllerdings müssen Arbeitnehmer den sicheren Umgang mit digitalen Tools lernen. Flexibilität und ständige Erreichbarkeit bringen aber auch Stress mit sich. Manche Menschen fühlen sich dadurch überfordert.\n\nEin weiteres wichtiges Thema ist der Datenschutz. Viele Nutzer machen sich Sorgen darüber, wie ihre persönlichen Daten verwendet werden. Deshalb ist es wichtig, über Risiken aufgeklärt zu werden und bewusst mit digitalen Medien umzugehen.\n\nAuch im Bildungsbereich schreitet die Digitalisierung voran. Schulen nutzen digitale Lernplattformen, um den Unterricht zu modernisieren. Schülerinnen und Schüler arbeiten zunehmend mit Tablets und digitalen Materialien.\nDie Digitalisierung bringt viele Chancen, aber auch Herausforderungen mit sich. Sie wird unser Leben auch in Zukunft stark beeinflussen.",

  "questions": [
    {
      "id": "q1",
      "question": "Was hat unser tägliches Leben stark verändert?",
      "options": ["Die Politik", "Die Globalisierung", "Die Digitalisierung", "Die Ernährung"],
      "answer": "Die Digitalisierung"
    },
    {
      "id": "q2",
      "question": "Was nutzen viele Menschen in ihrer Freizeit?",
      "options": ["Papier und Stift", "Digitale Geräte", "Bücher", "Zeitungen"],
      "answer": "Digitale Geräte"
    },

    {
      "id": "q7",
      "question": "Wo werden viele Dokumente gespeichert?",
      "options": ["Im Büro", "In der Cloud", "In Ordnern", "Auf USB-Sticks"],
      "answer": "In der Cloud"
    },
    {
      "id": "q8",
      "question": "Was müssen Arbeitnehmer lernen?",
      "options": ["Schneller tippen", "Kochen", "Mit digitalen Tools umgehen", "Langsamer sprechen"],
      "answer": "Mit digitalen Tools umgehen"
    },
    {
      "id": "q9",
      "question": "Was bringt die ständige Erreichbarkeit mit sich?",
      "options": ["Motivation", "Erholung", "Stress", "Mehr Freizeit"],
      "answer": "Stress"
    }

  ]
}


